tcxparser/__init__.py
tcxparser/exceptions.py
tcxparser/tcxparser.py
python_tcxparser-2.4.0.dist-info/AUTHORS.rst
python_tcxparser-2.4.0.dist-info/LICENSE
python_tcxparser-2.4.0.dist-info/METADATA
python_tcxparser-2.4.0.dist-info/WHEEL
python_tcxparser-2.4.0.dist-info/top_level.txt
python_tcxparser-2.4.0.dist-info/RECORD
